spider_cligen/__init__.py
spider_cligen/cli.py
spider_cligen/commands.py
spider_cligen/exceptions.py
spider_cligen/utils.py
spider_cligen/templates/README.md
spider_cligen/templates/__init__.py
spider_cligen/templates/circleci/__init__.py
spider_cligen/templates/circleci/config.yml
spider_cligen/templates/config/MANIFEST.in
spider_cligen/templates/config/__init__.py
spider_cligen/templates/config/pyproject.toml
spider_cligen/templates/config/setup.py
spider_cligen/templates/git/.gitignore
spider_cligen/templates/git/__init__.py
spider_cligen/templates/github/__init__.py
spider_cligen/templates/github/workflows/__init__.py
spider_cligen/templates/github/workflows/ci.yml
spider_cligen/templates/gitlab/.gitlab-ci.yml
spider_cligen/templates/gitlab/__init__.py
spider_cligen/templates/licenses/Apache.txt
spider_cligen/templates/licenses/BSD3Clause.txt
spider_cligen/templates/licenses/CCO.txt
spider_cligen/templates/licenses/GPLv3.txt
spider_cligen/templates/licenses/MIT.txt
spider_cligen/templates/licenses/__init__.py
tests/__init__.py
tests/test_utils.py
spider_cligen-0.1.8.dist-info/LICENSE
spider_cligen-0.1.8.dist-info/METADATA
spider_cligen-0.1.8.dist-info/WHEEL
spider_cligen-0.1.8.dist-info/entry_points.txt
spider_cligen-0.1.8.dist-info/top_level.txt
spider_cligen-0.1.8.dist-info/RECORD
