Metadata-Version: 2.1
Name: spider-cligen
Version: 0.1.8
Summary: A CLI tool to initialize Python projects with a standard structure.
Home-page: https://github.com/simondev413/SpiderCLI
Author: Simão Domingos De Oliveira António
Author-email: simaodomingos413@gamil.com
Project-URL: Source, https://github.com/simondev413/SpiderCLI/
Classifier: Programming Language :: Python :: 3
Classifier: License :: OSI Approved :: MIT License
Classifier: Operating System :: OS Independent
Requires-Python: >=3.9
License-File: LICENSE
Provides-Extra: docs
Requires-Dist: sphinx; extra == "docs"
Provides-Extra: test
Requires-Dist: pytest; extra == "test"
